igemwikiscraper/__init__.py
igemwikiscraper/__main__.py
igemwikiscraper/scraper.py
igemwikiscraper-0.5.1.dist-info/METADATA
igemwikiscraper-0.5.1.dist-info/RECORD
igemwikiscraper-0.5.1.dist-info/WHEEL
igemwikiscraper-0.5.1.dist-info/entry_points.txt
igemwikiscraper-0.5.1.dist-info/top_level.txt
