Metadata-Version: 2.1
Name: igemwikiscraper
Version: 0.5.1
Summary: GUI+CLI+Library webscraper built specifically for iGEM team wiki pages
Home-page: https://github.com/Virginia-iGEM/igem-wikiscraper
Author: Dylan Culfogienis
Author-email: dtc9bb@virginia.edu
License: MIT
Platform: UNKNOWN
Classifier: Development Status :: 4 - Beta
Classifier: Programming Language :: Python :: 3
Classifier: License :: OSI Approved :: MIT License
Classifier: Intended Audience :: Science/Research
Classifier: Operating System :: OS Independent
Requires-Dist: requests
Requires-Dist: beautifulsoup4
Requires-Dist: lxml
Requires-Dist: gooey (>=1.0.1)
